pep440/__init__.py
pep440/pep440.py
pep440_utility-0.1.0.dist-info/LICENSE
pep440_utility-0.1.0.dist-info/METADATA
pep440_utility-0.1.0.dist-info/WHEEL
pep440_utility-0.1.0.dist-info/RECORD
