Metadata-Version: 2.1
Name: pep440-utility
Version: 0.1.0
Summary: A utility for transitioning between version numbers based on PEP 440.
Home-page: https://github.com/azataiot/pep440
License: MIT
Keywords: packaging,pep440,versioning
Author: Azat
Author-email: 8280770+azataiot@users.noreply.github.com
Maintainer: Azat
Maintainer-email: 8280770+azataiot@users.noreply.github.com
Requires-Python: >=3.11,<4.0
Classifier: License :: OSI Approved :: MIT License
Classifier: Programming Language :: Python :: 3
Classifier: Programming Language :: Python :: 3.11
Classifier: Topic :: Software Development :: Build Tools
Classifier: Topic :: Software Development :: Libraries :: Python Modules
Project-URL: Repository, https://github.com/azataiot/pep440
